database_util/__init__.py
database_util/mysql_util.py
database_util_deepsec-1.0.2.dist-info/LICENSE
database_util_deepsec-1.0.2.dist-info/METADATA
database_util_deepsec-1.0.2.dist-info/WHEEL
database_util_deepsec-1.0.2.dist-info/top_level.txt
database_util_deepsec-1.0.2.dist-info/RECORD
